Transsmart_V2-0.1.data/scripts/transsmart
Transsmart_V2-0.1.dist-info/DESCRIPTION.rst
Transsmart_V2-0.1.dist-info/METADATA
Transsmart_V2-0.1.dist-info/RECORD
Transsmart_V2-0.1.dist-info/WHEEL
Transsmart_V2-0.1.dist-info/metadata.json
Transsmart_V2-0.1.dist-info/top_level.txt
transsmart/__init__.py
transsmart/account.py
transsmart/address.py
transsmart/authentication.py
transsmart/connection.py
transsmart/deliverytimes.py
transsmart/location.py
transsmart/prints.py
transsmart/rate.py
transsmart/shipment.py
transsmart/status.py
